MANIFEST.in
README.rst
setup.cfg
setup.py
pretix_mabel/__init__.py
pretix_mabel/frontend.py
pretix_mabel/models.py
pretix_mabel/paymentprovider.py
pretix_mabel/settings.py
pretix_mabel/signals.py
pretix_mabel/urls.py
pretix_mabel/views.py
pretix_mabel.egg-info/PKG-INFO
pretix_mabel.egg-info/SOURCES.txt
pretix_mabel.egg-info/dependency_links.txt
pretix_mabel.egg-info/entry_points.txt
pretix_mabel.egg-info/top_level.txt
pretix_mabel/locale/de/LC_MESSAGES/django.mo
pretix_mabel/locale/de/LC_MESSAGES/django.po
pretix_mabel/locale/de_Informal/.gitkeep
pretix_mabel/locale/de_Informal/LC_MESSAGES/django.mo
pretix_mabel/locale/de_Informal/LC_MESSAGES/django.po
pretix_mabel/migrations/0001_initial.py
pretix_mabel/migrations/0002_mabelsettings_ticketlimit.py
pretix_mabel/migrations/0003_remove_ticketlimit_event.py
pretix_mabel/migrations/0004_auto_20180109_1636.py
pretix_mabel/migrations/0005_auto_20180109_1637.py
pretix_mabel/migrations/0006_ticketlimit_event.py
pretix_mabel/migrations/__init__.py
pretix_mabel/static/pretix_mabel/.gitkeep
pretix_mabel/static/pretix_mabel/raven_icon.png
pretix_mabel/static/pretix_mabel/style.css
pretix_mabel/static/pretix_mabel/yI0Pyyi.jpg
pretix_mabel/static/pretix_mabel/js/CODE128.js
pretix_mabel/static/pretix_mabel/js/EAN_UPC.js
pretix_mabel/static/pretix_mabel/js/JsBarcode.js
pretix_mabel/static/pretix_mabel/js/blob-stream-v0.1.2.js
pretix_mabel/static/pretix_mabel/js/mabel-barcode.js
pretix_mabel/static/pretix_mabel/js/pdfkit-0.7.1.js
pretix_mabel/static/pretix_mabel/js/qrcode.min.js
pretix_mabel/static/pretix_mabel/js/underscore-min.js
pretix_mabel/templates/pretix_mabel/.gitkeep
pretix_mabel/templates/pretix_mabel/checkout_payment_form.html
pretix_mabel/templates/pretix_mabel/control.html
pretix_mabel/templates/pretix_mabel/control_cheque.html
pretix_mabel/templates/pretix_mabel/loginform.html
pretix_mabel/templates/pretix_mabel/order_pending.txt
pretix_mabel/templates/pretix_mabel/order_pending_cheque.txt
pretix_mabel/templates/pretix_mabel/pending.html
pretix_mabel/templates/pretix_mabel/pending_cheque.html
pretix_mabel/templates/pretix_mabel/settings.html
pretix_mabel/templates/pretix_mabel/tickets.html