Metadata-Version: 1.0
Name: pretix-mabel
Version: 1.0.11
Summary: Pretix customised for use at May Balls
Home-page: https://github.com/mabelticketing/pretix-mabel
Author: Christopher Little
Author-email: christopher@littlehq.uk
License: Apache Software License
Platform: UNKNOWN
